automation_anywhere/__init__.py
automation_anywhere/base.py
automation_anywhere/errors.py
automation_anywhere/executor.py
automation_anywhere-2.1.7.dist-info/LICENSE
automation_anywhere-2.1.7.dist-info/METADATA
automation_anywhere-2.1.7.dist-info/WHEEL
automation_anywhere-2.1.7.dist-info/top_level.txt
automation_anywhere-2.1.7.dist-info/RECORD
