Metadata-Version: 2.1
Name: automation-anywhere
Version: 2.1.7
Summary: A Python Package to deploy tasks on Automation Anywhere 360
Author-email: Mateus Interciso <minterciso@gmail.com>
Project-URL: Homepage, https://github.com/minterciso/pyAutomationAnywhere
Project-URL: Bug Tracker, https://github.com/minterciso/pyAutomationAnywhere/issues
Classifier: Programming Language :: Python :: 3
Classifier: License :: OSI Approved :: MIT License
Classifier: Operating System :: OS Independent
Requires-Python: >=3.9
License-File: LICENSE
